circles_file_iterator/__init__.py
circles_file_iterator/__main__.py
circles_file_iterator/global_variables/__init__.py
circles_file_iterator/global_variables/global_variables.py
circles_file_iterator/utils/__init__.py
circles_file_iterator/utils/cache.py
circles_file_iterator/utils/csv_cutting.py
circles_file_iterator/utils/cyverse_files.py
circles_file_iterator/utils/cyverse_io_irods.py
circles_file_iterator/utils/event_analysis.py
circles_file_iterator/utils/file_exploration.py
circles_file_iterator/utils/file_iterator.py
circles_file_iterator-1.1.2.dist-info/METADATA
circles_file_iterator-1.1.2.dist-info/WHEEL
circles_file_iterator-1.1.2.dist-info/top_level.txt
circles_file_iterator-1.1.2.dist-info/RECORD
