Metadata-Version: 2.1
Name: circles-file-iterator
Version: 1.1.2
Summary: Allows to iterate over CyVerse CIRCLES files
Home-page: https://github.com/codingrosquick/circles_file_handler
Author: Noe Carras
Author-email: carras.noe@gmail.com
License: MIT
Platform: UNKNOWN
Classifier: License :: OSI Approved :: MIT License
Classifier: Programming Language :: Python :: 3.8
Requires-Dist: build
Requires-Dist: certifi
Requires-Dist: charset-normalizer
Requires-Dist: click
Requires-Dist: commonmark
Requires-Dist: DateTime
Requires-Dist: defusedxml
Requires-Dist: docutils
Requires-Dist: Flask
Requires-Dist: idna
Requires-Dist: importlib-metadata
Requires-Dist: itsdangerous
Requires-Dist: Jinja2
Requires-Dist: keyring
Requires-Dist: MarkupSafe
Requires-Dist: mysql-connector-python
Requires-Dist: numpy
Requires-Dist: packaging
Requires-Dist: pandas
Requires-Dist: pep517
Requires-Dist: pkginfo
Requires-Dist: prettytable
Requires-Dist: protobuf
Requires-Dist: Pygments
Requires-Dist: pyparsing
Requires-Dist: python-dateutil
Requires-Dist: python-irodsclient
Requires-Dist: pytz
Requires-Dist: readme-renderer
Requires-Dist: requests
Requires-Dist: requests-toolbelt
Requires-Dist: rfc3986
Requires-Dist: rich
Requires-Dist: six
Requires-Dist: tomli
Requires-Dist: twine
Requires-Dist: typing-extensions
Requires-Dist: urllib3
Requires-Dist: wcwidth
Requires-Dist: webencodings
Requires-Dist: Werkzeug
Requires-Dist: zipp
Requires-Dist: zope.interface
